{"errors":[],"warnings":[],"namedChunkGroups":{"app":{"chunks":[12,10,4],"assets":["webpack-runtime-42966d4b934d3b9d8b90.js","webpack-runtime-42966d4b934d3b9d8b90.js.map","framework-95b680cb3190aa9bfe59.js","framework-95b680cb3190aa9bfe59.js.map","app-33f9e82a7dcd05b7a27b.js","app-33f9e82a7dcd05b7a27b.js.map"],"children":{},"childAssets":{}},"component---src-pages-404-js":{"chunks":[0,2,1,5],"assets":["1bfc9850-a98c0c6818dff7a1c233.js","1bfc9850-a98c0c6818dff7a1c233.js.map","d7eeaac4-55fb3421224c385e7d8c.js","d7eeaac4-55fb3421224c385e7d8c.js.map","commons-ecbb16fd13d93078109d.js","commons-ecbb16fd13d93078109d.js.map","component---src-pages-404-js-bd7d363aea123393c171.js","component---src-pages-404-js-bd7d363aea123393c171.js.map"],"children":{},"childAssets":{}},"component---src-pages-contacto-js":{"chunks":[0,2,3,1,6],"assets":["1bfc9850-a98c0c6818dff7a1c233.js","1bfc9850-a98c0c6818dff7a1c233.js.map","d7eeaac4-55fb3421224c385e7d8c.js","d7eeaac4-55fb3421224c385e7d8c.js.map","5e2a4920-3be0f59f89ccf9bf557b.js","5e2a4920-3be0f59f89ccf9bf557b.js.map","commons-ecbb16fd13d93078109d.js","commons-ecbb16fd13d93078109d.js.map","component---src-pages-contacto-js-55558a5525188841db64.js","component---src-pages-contacto-js-55558a5525188841db64.js.map"],"children":{},"childAssets":{}},"component---src-pages-index-js":{"chunks":[11,0,2,1,7],"assets":["styles.d1794d988f89653b40d2.css","styles-24c541b6ac347bae38f1.js","styles-24c541b6ac347bae38f1.js.map","1bfc9850-a98c0c6818dff7a1c233.js","1bfc9850-a98c0c6818dff7a1c233.js.map","d7eeaac4-55fb3421224c385e7d8c.js","d7eeaac4-55fb3421224c385e7d8c.js.map","commons-ecbb16fd13d93078109d.js","commons-ecbb16fd13d93078109d.js.map","component---src-pages-index-js-5d43d7c2f62884b120f2.js","component---src-pages-index-js-5d43d7c2f62884b120f2.js.map"],"children":{},"childAssets":{}},"component---src-pages-proyectos-js":{"chunks":[0,2,1,8],"assets":["1bfc9850-a98c0c6818dff7a1c233.js","1bfc9850-a98c0c6818dff7a1c233.js.map","d7eeaac4-55fb3421224c385e7d8c.js","d7eeaac4-55fb3421224c385e7d8c.js.map","commons-ecbb16fd13d93078109d.js","commons-ecbb16fd13d93078109d.js.map","component---src-pages-proyectos-js-56164e60d37a3e9a2936.js","component---src-pages-proyectos-js-56164e60d37a3e9a2936.js.map"],"children":{},"childAssets":{}},"component---src-pages-using-typescript-tsx":{"chunks":[0,2,1,9],"assets":["1bfc9850-a98c0c6818dff7a1c233.js","1bfc9850-a98c0c6818dff7a1c233.js.map","d7eeaac4-55fb3421224c385e7d8c.js","d7eeaac4-55fb3421224c385e7d8c.js.map","commons-ecbb16fd13d93078109d.js","commons-ecbb16fd13d93078109d.js.map","component---src-pages-using-typescript-tsx-5fe6ae92c3b4212a94ed.js","component---src-pages-using-typescript-tsx-5fe6ae92c3b4212a94ed.js.map"],"children":{},"childAssets":{}}},"assetsByChunkName":{"app":["webpack-runtime-42966d4b934d3b9d8b90.js","framework-95b680cb3190aa9bfe59.js","app-33f9e82a7dcd05b7a27b.js"],"component---src-pages-404-js":["1bfc9850-a98c0c6818dff7a1c233.js","d7eeaac4-55fb3421224c385e7d8c.js","commons-ecbb16fd13d93078109d.js","component---src-pages-404-js-bd7d363aea123393c171.js"],"component---src-pages-contacto-js":["1bfc9850-a98c0c6818dff7a1c233.js","d7eeaac4-55fb3421224c385e7d8c.js","5e2a4920-3be0f59f89ccf9bf557b.js","commons-ecbb16fd13d93078109d.js","component---src-pages-contacto-js-55558a5525188841db64.js"],"component---src-pages-index-js":["styles.d1794d988f89653b40d2.css","styles-24c541b6ac347bae38f1.js","1bfc9850-a98c0c6818dff7a1c233.js","d7eeaac4-55fb3421224c385e7d8c.js","commons-ecbb16fd13d93078109d.js","component---src-pages-index-js-5d43d7c2f62884b120f2.js"],"component---src-pages-proyectos-js":["1bfc9850-a98c0c6818dff7a1c233.js","d7eeaac4-55fb3421224c385e7d8c.js","commons-ecbb16fd13d93078109d.js","component---src-pages-proyectos-js-56164e60d37a3e9a2936.js"],"component---src-pages-using-typescript-tsx":["1bfc9850-a98c0c6818dff7a1c233.js","d7eeaac4-55fb3421224c385e7d8c.js","commons-ecbb16fd13d93078109d.js","component---src-pages-using-typescript-tsx-5fe6ae92c3b4212a94ed.js"]}}